pobj/__init__.py
pobj-1.1.1.dist-info/LICENSE.txt
pobj-1.1.1.dist-info/METADATA
pobj-1.1.1.dist-info/WHEEL
pobj-1.1.1.dist-info/top_level.txt
pobj-1.1.1.dist-info/RECORD
